news_toolkit_api/__init__.py
news_toolkit_api/api/__init__.py
news_toolkit_api/api/v1/__init__.py
news_toolkit_api/api/v1/db.py
news_toolkit_api/api/v1/injected.py
news_toolkit_api/api/v1/middlewares.py
news_toolkit_api/api/v1/response/__init__.py
news_toolkit_api/api/v1/response/article.py
news_toolkit_api/api/v1/response/category.py
news_toolkit_api/api/v1/response/feed.py
news_toolkit_api/api/v1/response/related_articles.py
news_toolkit_api/api/v1/response/subscription.py
news_toolkit_api/api/v1/routers.py
news_toolkit_api/app.py
news_toolkit_api/background_tasks/__init__.py
news_toolkit_api/background_tasks/article.py
news_toolkit_api/background_tasks/feed.py
news_toolkit_api/background_tasks/utils.py
news_toolkit_api/config/__init__.py
news_toolkit_api/config/settings.py
news_toolkit_api/db/__init__.py
news_toolkit_api/db/article.py
news_toolkit_api/db/category.py
news_toolkit_api/db/feed.py
news_toolkit_api/db/subscription.py
news_toolkit_api/news_blocks/__init__.py
news_toolkit_api/news_blocks/article_introduction_block.py
news_toolkit_api/news_blocks/banner_ad_block.py
news_toolkit_api/news_blocks/block_type.py
news_toolkit_api/news_blocks/navigate_to_article.py
news_toolkit_api/news_blocks/section_header_block.py
news_toolkit_api/news_blocks/text_lead_paragraph_block.py
news_toolkit_api/repository/__init__.py
news_toolkit_api/repository/article.py
news_toolkit_api/repository/feed.py
news_toolkit_api/repository/interface.py
news_toolkit_api/tool/__init__.py
news_toolkit_api/tool/populate_categories.py
news_toolkit_api/utils.py
news_toolkit_api-1.0.1.dist-info/METADATA
news_toolkit_api-1.0.1.dist-info/WHEEL
news_toolkit_api-1.0.1.dist-info/RECORD
