Metadata-Version: 2.1
Name: news-toolkit-api
Version: 1.0.1
Summary: 
Author: wakita181009
Author-email: wakita181009@gmail.com
Requires-Python: >=3.12,<4.0
Classifier: Programming Language :: Python :: 3
Classifier: Programming Language :: Python :: 3.12
Requires-Dist: aiohttp (>=3.8.5,<4.0.0)
Requires-Dist: beautifulsoup4 (>=4.12.2,<5.0.0)
Requires-Dist: fastapi (>=0.108.0,<0.109.0)
Requires-Dist: google-cloud-ndb (>=2.2.0,<3.0.0)
Requires-Dist: html5lib (>=1.1,<2.0)
Requires-Dist: injector (>=0.21.0,<0.22.0)
